declarative_requirements/__init__.py
declarative_requirements/integration.py
declarative_requirements/version.py
setuptools_declarative_requirements-1.3.0.dist-info/LICENSE
setuptools_declarative_requirements-1.3.0.dist-info/METADATA
setuptools_declarative_requirements-1.3.0.dist-info/WHEEL
setuptools_declarative_requirements-1.3.0.dist-info/entry_points.txt
setuptools_declarative_requirements-1.3.0.dist-info/top_level.txt
setuptools_declarative_requirements-1.3.0.dist-info/RECORD
