Metadata-Version: 2.1
Name: setuptools-declarative-requirements
Version: 1.3.0
Summary: File support for setuptools declarative setup.cfg
Home-page: https://github.com/s0undt3ch/setuptools-declarative-requirements
Author: Pedro Algarvio
Author-email: pedro@algarvio.me
License: Apache Software License 2.0
Project-URL: Source, https://github.com/s0undt3ch/setuptools-declarative-requirements
Project-URL: Tracker, https://github.com/s0undt3ch/setuptools-declarative-requirements/issues
Platform: unix
Platform: linux
Platform: osx
Platform: cygwin
Platform: win32
Classifier: Programming Language :: Python
Classifier: Programming Language :: Cython
Classifier: Programming Language :: Python :: 3
Classifier: Programming Language :: Python :: 3 :: Only
Classifier: Programming Language :: Python :: 3.5
Classifier: Programming Language :: Python :: 3.6
Classifier: Programming Language :: Python :: 3.7
Classifier: Programming Language :: Python :: 3.8
Classifier: Programming Language :: Python :: 3.9
Classifier: Development Status :: 4 - Beta
Classifier: Intended Audience :: Developers
Classifier: License :: OSI Approved :: Apache Software License
Requires-Python: >=3.5
License-File: LICENSE
Requires-Dist: setuptools
